LICENSE
MANIFEST.in
README.rst
requirements.txt
setup.cfg
setup.py
version.txt
spatial_interpolators/PvQv_C.pyx
spatial_interpolators/__init__.py
spatial_interpolators/barnes_objective.py
spatial_interpolators/biharmonic_spline.py
spatial_interpolators/compact_radial_basis.py
spatial_interpolators/inpaint.py
spatial_interpolators/legendre.py
spatial_interpolators/radial_basis.py
spatial_interpolators/shepard_interpolant.py
spatial_interpolators/spatial.py
spatial_interpolators/sph_bilinear.py
spatial_interpolators/sph_radial_basis.py
spatial_interpolators/sph_spline.py
spatial_interpolators/version.py
spatial_interpolators.egg-info/PKG-INFO
spatial_interpolators.egg-info/SOURCES.txt
spatial_interpolators.egg-info/dependency_links.txt
spatial_interpolators.egg-info/requires.txt
spatial_interpolators.egg-info/top_level.txt