Metadata-Version: 2.1
Name: spatial-interpolators
Version: 1.0.0.4
Summary: Spatial interpolation tools for Python
Home-page: https://github.com/tsutterley/spatial-interpolators
Author: Tyler Sutterley
Author-email: tsutterl@uw.edu
License: MIT
Keywords: spatial interpolation,regridding,regridding over a sphere
Classifier: Development Status :: 3 - Alpha
Classifier: Intended Audience :: Science/Research
Classifier: Topic :: Scientific/Engineering :: Physics
Classifier: License :: OSI Approved :: MIT License
Classifier: Programming Language :: Python :: 3
Classifier: Programming Language :: Python :: 3.6
Classifier: Programming Language :: Python :: 3.7
Classifier: Programming Language :: Python :: 3.8
License-File: LICENSE
